{
  "table": [
    {
      "isBusy": false,
      "id": 1,
      "recipeId": 0,
      "floor": "Floor 1",
      "name": "Table 1"
    },
    {
      "isBusy": false,
      "id": 2,
      "recipeId": 0,
      "floor": "Floor 2",
      "name": "Table 1"
    },
    {
      "isBusy": false,
      "id": 3,
      "recipeId": 0,
      "floor": "Floor 1",
      "name": "Table 2"
    }
  ],
  "sale": [
    {
      "id": 2014,
      "year": 2014,
      "amount": 30,
      "colorcode": "darkred"
    },
    {
      "year": 2012,
      "amount": 50,
      "colorcode": "blue"
    },
    {
      "year": 2013,
      "amount": 150,
      "colorcode": "green"
    },
    {
      "year": 2015,
      "amount": 200,
      "colorcode": "gray"
    },
    {
      "year": 2011,
      "amount": 100,
      "colorcode": "black"
    }
  ],
  "menu": [
    {
      "name": "Hamburger ",
      "price": 5,
      "outStock": 0.2,
      "id": 1,
      "ingredient": "beef",
      "category": "Fast-Food",
      "iconSrc": "burger.png"
    },
    {
      "name": "pizza",
      "price": 10,
      "outStock": 0.5,
      "id": 2,
      "ingredient": "pork",
      "category": "Fast-Food",
      "iconSrc": "pizza.png"
    },
    {
      "price": 2,
      "outStock": 0.2,
      "name": "sandwich ",
      "id": 3,
      "ingredient": "beef",
      "category": "Fast-Food",
      "iconSrc": "taco.png"
    },
    {
      "name": "soup",
      "ingredient": "duck",
      "category": "Fast-Food",
      "price": 5,
      "outStock": 0.5,
      "id": 18,
      "iconSrc": "ramen.png"
    }
  ],
  "ingredient": [
    {
      "name": "beef",
      "value": "12",
      "id": 9
    },
    {
      "name": "chicken",
      "value": "12",
      "id": 10
    },
    {
      "name": "pork",
      "value": "12",
      "id": 11
    },
    {
      "name": "duck",
      "value": "10",
      "id": 12
    },
    {
      "name": "leng",
      "value": "1",
      "id": 13
    }
  ],
  "stock": [
    {
      "ingredient": "beef",
      "value": 16,
      "id": 1,
      "newValue": 0,
      "issum": false
    },
    {
      "ingredient": "chicken",
      "value": "12",
      "id": 2
    },
    {
      "ingredient": "pork",
      "value": "35",
      "id": 3
    },
    {
      "ingredient": "duck",
      "value": "45",
      "id": 4
    }
  ],
  "user": [
    {
      "firstname": "chhour",
      "lastname": "chhayleng",
      "email": "chhourchhayleng@gmail.com",
      "password": "1234",
      "confirmpassword": "1234",
      "id": 4
    },
    {
      "firstname": "leng",
      "lastname": "leng",
      "email": "leng@gmail.com",
      "password": "1234",
      "confirmpassword": "1234",
      "id": 7
    },
    {
      "firstname": "leng",
      "lastname": "leng",
      "email": "leng@gmail.com",
      "password": "1234",
      "confirmpassword": "1234",
      "id": 8
    },
    {
      "firstname": "leng",
      "lastname": "chhay",
      "email": "leng@gmail.com",
      "password": "1234567",
      "confirmpassword": "1234567",
      "id": 9
    },
    {
      "firstname": "leng",
      "lastname": "chhay",
      "email": "leng@gmail.com",
      "password": "123456789",
      "confirmpassword": "123456789",
      "id": 10
    },
    {
      "firstname": "chhay",
      "lastname": "leng123",
      "email": "lengxxxx@gmail.com",
      "password": "12345678",
      "confirmpassword": "12345678",
      "id": 11
    },
    {
      "firstname": "chhay",
      "lastname": "leng",
      "email": "lengxxxx@gmail.com",
      "password": "12345678",
      "confirmpassword": "12345678",
      "id": 12
    },
    {
      "firstname": "chhay",
      "lastname": "leng",
      "email": "lengxxxx@gmail.com",
      "password": "12345",
      "confirmpassword": "12345",
      "id": 13
    }
  ],
  "category": [
    {
      "menu": "Fast-Food",
      "id": 1
    },
    {
      "menu": "drink",
      "id": 2
    },
    {
      "menu": "Food",
      "id": 3
    },
    {
      "menu": "Late-Food",
      "name": "leng",
      "id": 4
    },
    {
      "menu": "leng",
      "name": "leng",
      "id": 5
    }
  ],
  "recipe": [
    {
      "order": [
        {
          "name": "soup",
          "units": 1,
          "id": 18,
          "price": 5,
          "isHave": true,
          "date": "2023-10-11T09:29:54.446Z",
          "granTotal": 0,
          "grandUnits": 0
        },
        {
          "name": "sandwich ",
          "units": 2,
          "id": 3,
          "price": 2,
          "isHave": true,
          "date": "2023-10-11T09:29:54.446Z",
          "granTotal": 5,
          "grandUnits": 1
        },
        {
          "name": "pizza",
          "units": 2,
          "id": 2,
          "price": 10,
          "isHave": true,
          "date": "2023-10-11T09:29:54.446Z",
          "granTotal": 7,
          "grandUnits": 2
        },
        {
          "name": "Hamburger ",
          "units": 1,
          "id": 1,
          "price": 5,
          "isHave": true,
          "date": "2023-10-11T09:29:54.446Z",
          "granTotal": 17,
          "grandUnits": 3
        }
      ],
      "id": 150
    },
    {
      "order": [
        {
          "name": "pizza",
          "units": 1,
          "id": 2,
          "price": "10",
          "isHave": true,
          "date": "2023-10-17T09:09:02.033Z",
          "granTotal": 0,
          "grandUnits": 0
        },
        {
          "name": "Hamburger ",
          "units": 1,
          "id": 1,
          "price": "5",
          "isHave": true,
          "date": "2023-10-17T09:09:02.033Z",
          "granTotal": 10,
          "grandUnits": 1
        },
        {
          "name": "sandwich ",
          "units": 1,
          "id": 3,
          "price": "2",
          "isHave": true,
          "date": "2023-10-17T09:09:02.033Z",
          "granTotal": 15,
          "grandUnits": 2
        }
      ],
      "id": 151
    },
    {
      "order": [
        {
          "name": "soup",
          "units": 2,
          "id": 18,
          "price": 5,
          "isHave": true,
          "date": "2023-10-17T09:15:30.694Z",
          "granTotal": 0,
          "grandUnits": 0
        },
        {
          "name": "sandwich ",
          "units": 1,
          "id": 3,
          "price": 2,
          "isHave": true,
          "date": "2023-10-17T09:18:16.656Z",
          "granTotal": 10,
          "grandUnits": 2
        }
      ],
      "id": 153
    },
    {
      "order": [
        {
          "name": "soup",
          "units": 1,
          "id": 18,
          "price": 5,
          "isHave": true,
          "date": "2023-10-17T09:20:19.756Z",
          "granTotal": 0,
          "grandUnits": 0
        }
      ],
      "id": 154
    },
    {
      "order": [
        {
          "name": "sandwich ",
          "units": 1,
          "id": 3,
          "price": 2,
          "isHave": true,
          "date": "2023-10-17T09:21:02.162Z",
          "granTotal": 0,
          "grandUnits": 0
        },
        {
          "name": "soup",
          "units": 1,
          "id": 18,
          "price": 5,
          "isHave": true,
          "date": "2023-10-17T09:21:02.162Z",
          "granTotal": 2,
          "grandUnits": 1
        }
      ],
      "id": 155
    },
    {
      "order": [
        {
          "name": "soup",
          "units": 2,
          "id": 18,
          "price": 5,
          "isHave": true,
          "date": "2023-10-17T09:21:50.086Z",
          "granTotal": 0,
          "grandUnits": 0
        },
        {
          "name": "sandwich ",
          "units": 1,
          "id": 3,
          "price": 2,
          "isHave": true,
          "date": "2023-10-17T09:21:50.086Z",
          "granTotal": 5,
          "grandUnits": 1
        }
      ],
      "id": 156
    },
    {
      "order": [
        {
          "name": "soup",
          "units": 1,
          "id": 18,
          "price": 5,
          "isHave": true,
          "date": "2023-10-17T09:22:58.123Z",
          "granTotal": 0,
          "grandUnits": 0
        }
      ],
      "id": 157
    },
    {
      "order": [],
      "id": 158
    },
    {
      "order": [
        {
          "name": "soup",
          "units": 1,
          "id": 18,
          "price": 5,
          "isHave": true,
          "date": "2023-10-17T09:30:50.041Z",
          "granTotal": 0,
          "grandUnits": 0
        }
      ],
      "id": 160
    },
    {
      "order": [
        {
          "name": "soup",
          "units": 1,
          "id": 18,
          "price": 5,
          "isHave": true,
          "date": "2023-10-17T09:39:07.522Z",
          "granTotal": 0,
          "grandUnits": 0
        },
        {
          "name": "sandwich ",
          "units": 1,
          "id": 3,
          "price": 2,
          "isHave": true,
          "date": "2023-10-17T09:39:07.522Z",
          "granTotal": 5,
          "grandUnits": 1
        }
      ],
      "id": 164
    },
    {
      "order": [
        {
          "name": "soup",
          "units": 1,
          "id": 18,
          "price": 5,
          "isHave": true,
          "date": "2023-10-17T09:41:16.340Z",
          "granTotal": 0,
          "grandUnits": 0
        },
        {
          "name": "sandwich ",
          "units": 1,
          "id": 3,
          "price": 2,
          "isHave": true,
          "date": "2023-10-17T09:41:16.340Z",
          "granTotal": 5,
          "grandUnits": 1
        }
      ],
      "id": 165
    },
    {
      "order": [
        {
          "name": "soup",
          "units": 2,
          "id": 18,
          "price": 5,
          "isHave": true,
          "date": "2023-10-17T09:47:02.406Z",
          "granTotal": 0,
          "grandUnits": 0
        },
        {
          "name": "sandwich ",
          "units": 1,
          "id": 3,
          "price": 2,
          "isHave": true,
          "date": "2023-10-17T09:47:02.406Z",
          "granTotal": 5,
          "grandUnits": 1
        },
        {
          "name": "bean",
          "units": 1,
          "id": 19,
          "price": 2,
          "isHave": true,
          "date": "2023-10-18T01:13:53.696Z",
          "granTotal": 7,
          "grandUnits": 2
        }
      ],
      "id": 166
    },
    {
      "order": [
        {
          "name": "soup",
          "units": 1,
          "id": 18,
          "price": 5,
          "isHave": true,
          "date": "2023-10-17T09:48:55.097Z",
          "granTotal": 0,
          "grandUnits": 0
        },
        {
          "name": "sandwich ",
          "units": 1,
          "id": 3,
          "price": 2,
          "isHave": true,
          "date": "2023-10-17T09:48:55.097Z",
          "granTotal": 5,
          "grandUnits": 1
        }
      ],
      "id": 169
    },
    {
      "order": [
        {
          "name": "soup",
          "units": 1,
          "id": 18,
          "price": 5,
          "isHave": true,
          "date": "2023-10-18T02:06:53.521Z",
          "granTotal": 0,
          "grandUnits": 0
        }
      ],
      "id": 170
    },
    {
      "order": [
        {
          "name": "sandwich ",
          "units": 1,
          "id": 3,
          "price": 2,
          "isHave": true,
          "date": "2023-10-18T02:07:50.081Z",
          "granTotal": 0,
          "grandUnits": 0
        }
      ],
      "id": 171
    },
    {
      "order": [
        {
          "name": "sandwich ",
          "units": 6,
          "id": 3,
          "price": 2,
          "isHave": true,
          "date": "2023-10-19T08:38:57.728Z",
          "granTotal": 0,
          "grandUnits": 0
        }
      ],
      "id": 172
    },
    {
      "order": [
        {
          "name": "sandwich ",
          "units": 1,
          "id": 3,
          "price": 2,
          "isHave": true,
          "date": "2023-10-19T08:39:03.371Z",
          "granTotal": 0,
          "grandUnits": 0
        }
      ],
      "id": 173
    },
    {
      "order": [
        {
          "name": "sandwich ",
          "units": 1,
          "id": 3,
          "price": 2,
          "isHave": true,
          "date": "2023-10-19T08:40:34.961Z",
          "granTotal": 0,
          "grandUnits": 0
        }
      ],
      "id": 174
    },
    {
      "order": [
        {
          "name": "soup",
          "units": 1,
          "id": 18,
          "price": 5,
          "isHave": true,
          "date": "2023-10-20T03:10:10.061Z",
          "granTotal": 0,
          "grandUnits": 0
        },
        {
          "name": "sandwich ",
          "units": 1,
          "id": 3,
          "price": 2,
          "isHave": true,
          "date": "2023-10-20T03:10:10.061Z",
          "granTotal": 5,
          "grandUnits": 1
        },
        {
          "name": "Hamburger ",
          "units": 1,
          "id": 1,
          "price": 5,
          "isHave": true,
          "date": "2023-10-20T03:10:10.061Z",
          "granTotal": 7,
          "grandUnits": 2
        },
        {
          "name": "bean",
          "units": 1,
          "id": 19,
          "price": 2,
          "isHave": true,
          "date": "2023-10-20T03:10:10.061Z",
          "granTotal": 12,
          "grandUnits": 3
        }
      ],
      "id": 175
    },
    {
      "order": [
        {
          "name": "soup",
          "units": 1,
          "id": 18,
          "price": 5,
          "isHave": true,
          "date": "2023-10-20T03:45:18.898Z",
          "granTotal": 0,
          "grandUnits": 0
        },
        {
          "name": "sandwich ",
          "units": 2,
          "id": 3,
          "price": 2,
          "isHave": true,
          "date": "2023-10-20T03:45:18.898Z",
          "granTotal": 5,
          "grandUnits": 1
        }
      ],
      "id": 176
    },
    {
      "order": [
        {
          "name": "cafee",
          "units": 1,
          "id": 20,
          "price": 4,
          "isHave": true,
          "date": "2023-10-27T01:42:43.170Z",
          "granTotal": 0,
          "grandUnits": 0
        }
      ],
      "id": 178
    },
    {
      "order": [
        {
          "name": "Hamburger ",
          "units": 1,
          "id": 1,
          "price": 5,
          "isHave": true,
          "date": "2024-02-05T09:17:19.463Z",
          "granTotal": 0,
          "grandUnits": 0
        },
        {
          "name": "pizza",
          "units": 1,
          "id": 2,
          "price": 10,
          "isHave": true,
          "date": "2024-02-05T09:17:19.463Z",
          "granTotal": 5,
          "grandUnits": 1
        },
        {
          "name": "sandwich ",
          "units": 1,
          "id": 3,
          "price": 2,
          "isHave": true,
          "date": "2024-02-05T09:17:19.463Z",
          "granTotal": 15,
          "grandUnits": 2
        },
        {
          "name": "soup",
          "units": 1,
          "id": 18,
          "price": 5,
          "isHave": true,
          "date": "2024-02-05T09:17:19.463Z",
          "granTotal": 17,
          "grandUnits": 3
        },
        {
          "name": "bean",
          "units": 1,
          "id": 19,
          "price": 2,
          "isHave": true,
          "date": "2024-02-05T09:17:19.463Z",
          "granTotal": 22,
          "grandUnits": 4
        }
      ],
      "id": 179
    },
    {
      "order": [
        {
          "name": "soup",
          "units": 1,
          "id": 18,
          "price": 5,
          "isHave": true,
          "date": "2024-02-06T02:42:08.664Z",
          "granTotal": 0,
          "grandUnits": 0
        },
        {
          "name": "bean",
          "units": 1,
          "id": 19,
          "price": 2,
          "isHave": true,
          "date": "2024-02-06T02:42:08.664Z",
          "granTotal": 5,
          "grandUnits": 1
        }
      ],
      "id": 180
    },
    {
      "order": [
        {
          "name": "pizza",
          "units": 1,
          "id": 2,
          "price": 10,
          "isHave": true,
          "date": "2024-02-21T01:39:12.561Z",
          "granTotal": 0,
          "grandUnits": 0
        },
        {
          "name": "sandwich ",
          "units": 1,
          "id": 3,
          "price": 2,
          "isHave": true,
          "date": "2024-02-21T01:39:12.561Z",
          "granTotal": 10,
          "grandUnits": 1
        },
        {
          "name": "soup",
          "units": 1,
          "id": 18,
          "price": 5,
          "isHave": true,
          "date": "2024-02-21T01:39:12.561Z",
          "granTotal": 12,
          "grandUnits": 2
        },
        {
          "name": "bean",
          "units": 1,
          "id": 19,
          "price": 2,
          "isHave": true,
          "date": "2024-02-21T01:39:12.561Z",
          "granTotal": 17,
          "grandUnits": 3
        }
      ],
      "id": 182
    },
    {
      "order": [
        {
          "name": "cafee",
          "units": 1,
          "id": 20,
          "price": 4,
          "isHave": true,
          "date": "2024-02-21T01:54:14.019Z",
          "granTotal": 0,
          "grandUnits": 0
        },
        {
          "name": "sandwich ",
          "units": 1,
          "id": 3,
          "price": 2,
          "isHave": true,
          "date": "2024-02-21T01:54:14.019Z",
          "granTotal": 4,
          "grandUnits": 1
        },
        {
          "name": "Hamburger ",
          "units": 2,
          "id": 1,
          "price": 5,
          "isHave": true,
          "date": "2024-02-21T01:54:14.019Z",
          "granTotal": 6,
          "grandUnits": 2
        },
        {
          "name": "pizza",
          "units": 1,
          "id": 2,
          "price": 10,
          "isHave": true,
          "date": "2024-03-21T05:33:32.199Z",
          "granTotal": 11,
          "grandUnits": 3
        },
        {
          "name": "soup",
          "units": 1,
          "id": 18,
          "price": 5,
          "isHave": true,
          "date": "2024-03-21T05:33:32.199Z",
          "granTotal": 26,
          "grandUnits": 5
        }
      ],
      "id": 183
    },
    {
      "order": [
        {
          "name": "bean",
          "units": 1,
          "id": 19,
          "price": 2,
          "isHave": true,
          "date": "2024-03-21T07:18:56.418Z",
          "granTotal": 0,
          "grandUnits": 0
        },
        {
          "name": "soup",
          "units": 1,
          "id": 18,
          "price": 5,
          "isHave": true,
          "date": "2024-03-21T07:18:56.418Z",
          "granTotal": 2,
          "grandUnits": 1
        },
        {
          "name": "sandwich ",
          "units": 1,
          "id": 3,
          "price": 2,
          "isHave": true,
          "date": "2024-03-21T07:18:56.418Z",
          "granTotal": 7,
          "grandUnits": 2
        },
        {
          "name": "pizza",
          "units": 1,
          "id": 2,
          "price": 10,
          "isHave": true,
          "date": "2024-03-21T07:18:56.418Z",
          "granTotal": 9,
          "grandUnits": 3
        },
        {
          "name": "Hamburger ",
          "units": 1,
          "id": 1,
          "price": 5,
          "isHave": true,
          "date": "2024-03-21T07:18:56.418Z",
          "granTotal": 19,
          "grandUnits": 4
        }
      ],
      "id": 184
    },
    {
      "order": [
        {
          "name": "soup",
          "units": 1,
          "id": 18,
          "price": 5,
          "isHave": true,
          "date": "2024-03-28T02:15:46.552Z",
          "granTotal": 0,
          "grandUnits": 0
        },
        {
          "name": "sandwich ",
          "units": 1,
          "id": 3,
          "price": 2,
          "isHave": true,
          "date": "2024-03-28T02:15:46.552Z",
          "granTotal": 5,
          "grandUnits": 1
        },
        {
          "name": "pizza",
          "units": 1,
          "id": 2,
          "price": 10,
          "isHave": true,
          "date": "2024-03-28T02:15:46.552Z",
          "granTotal": 7,
          "grandUnits": 2
        },
        {
          "name": "Hamburger ",
          "units": 1,
          "id": 1,
          "price": 5,
          "isHave": true,
          "date": "2024-03-28T02:15:46.552Z",
          "granTotal": 17,
          "grandUnits": 3
        }
      ],
      "id": 186
    },
    {
      "order": [
        {
          "name": "soup",
          "units": 1,
          "id": 18,
          "price": 5,
          "isHave": true,
          "date": "2024-03-28T08:29:54.623Z",
          "granTotal": 0,
          "grandUnits": 0
        },
        {
          "name": "sandwich ",
          "units": 1,
          "id": 3,
          "price": 2,
          "isHave": true,
          "date": "2024-03-28T08:29:54.623Z",
          "granTotal": 5,
          "grandUnits": 1
        },
        {
          "name": "pizza",
          "units": 1,
          "id": 2,
          "price": 10,
          "isHave": true,
          "date": "2024-03-28T08:29:54.623Z",
          "granTotal": 7,
          "grandUnits": 2
        },
        {
          "name": "Hamburger ",
          "units": 1,
          "id": 1,
          "price": 5,
          "isHave": true,
          "date": "2024-03-28T08:29:54.623Z",
          "granTotal": 17,
          "grandUnits": 3
        }
      ],
      "id": 189
    },
    {
      "order": [
        {
          "name": "soup",
          "units": 3,
          "id": 18,
          "price": 5,
          "isHave": true,
          "date": "2024-03-29T07:09:56.521Z",
          "granTotal": 0,
          "grandUnits": 0
        },
        {
          "name": "sandwich ",
          "units": 4,
          "id": 3,
          "price": 2,
          "isHave": true,
          "date": "2024-03-29T07:09:56.521Z",
          "granTotal": 5,
          "grandUnits": 1
        },
        {
          "name": "pizza",
          "units": 10,
          "id": 2,
          "price": 10,
          "isHave": true,
          "date": "2024-03-29T07:09:56.521Z",
          "granTotal": 7,
          "grandUnits": 2
        },
        {
          "name": "Hamburger ",
          "units": 2,
          "id": 1,
          "price": 5,
          "isHave": true,
          "date": "2024-03-29T07:09:56.521Z",
          "granTotal": 17,
          "grandUnits": 3
        }
      ],
      "id": 190
    },
    {
      "order": [
        {
          "name": "soup",
          "units": 1,
          "id": 18,
          "price": 5,
          "isHave": true,
          "date": "2024-04-02T01:55:15.305Z",
          "granTotal": 0,
          "grandUnits": 0
        },
        {
          "name": "sandwich ",
          "units": 1,
          "id": 3,
          "price": 2,
          "isHave": true,
          "date": "2024-04-02T01:55:15.305Z",
          "granTotal": 5,
          "grandUnits": 1
        },
        {
          "name": "pizza",
          "units": 1,
          "id": 2,
          "price": 10,
          "isHave": true,
          "date": "2024-04-02T01:55:15.305Z",
          "granTotal": 7,
          "grandUnits": 2
        },
        {
          "name": "Hamburger ",
          "units": 1,
          "id": 1,
          "price": 5,
          "isHave": true,
          "date": "2024-04-02T01:55:15.305Z",
          "granTotal": 17,
          "grandUnits": 3
        }
      ],
      "id": 191
    }
  ],
  "notifi": [],
  "qr": [
    {
      "isView": false,
      "name": "ing ing",
      "description": "lalalala",
      "start_date": "12.32.2040",
      "end_date": "12.33.2050",
      "id": 5
    },
    {
      "isView": false,
      "name": "admin",
      "description": "status",
      "end_date": "12.12.22",
      "start_date": "13.13.23",
      "id": 6
    }
  ],
  "attender": [
    {
      "name": "admin",
      "honor": "hahahaha",
      "gender": "m",
      "status": "active",
      "category": "it",
      "id": 2
    }
  ],
  "attender_category": [
    {
      "id": 1,
      "name": "admin",
      "description": "hello",
      "createdate": "12.12.2022",
      "createby": "noname"
    },
    {
      "name": "addmin",
      "description": "Low",
      "createdate": "12/21/22",
      "createby": "IT",
      "id": 2
    }
  ]
}